solidipy_mipt/__init__.py
solidipy_mipt/_metrics.py
solidipy_mipt/_selection.py
solidipy_mipt/algorithms/__init__.py
solidipy_mipt/algorithms/_np_regressor.py
solidipy_mipt/algorithms/_predictor_abc.py
solidipy_mipt/algorithms/_wknn.py
solidipy_mipt/algorithms/utils/__init__.py
solidipy_mipt/algorithms/utils/distance.py
solidipy_mipt/utils/__init__.py
solidipy_mipt/utils/errors.py
solidipy_mipt/utils/validate.py
solidipy_mipt/visualization/__init__.py
solidipy_mipt/visualization/_utils.py
solidipy_mipt/visualization/base_diagrams.py
solidipy_mipt/visualization/colors.py
solidipy_mipt/visualization/comparison.py
solidipy_mipt/visualization/distribution.py
solidipy_mipt/visualization/regression.py
solidipy_mipt-1.2.3.dist-info/LICENSE.txt
solidipy_mipt-1.2.3.dist-info/METADATA
solidipy_mipt-1.2.3.dist-info/WHEEL
solidipy_mipt-1.2.3.dist-info/top_level.txt
solidipy_mipt-1.2.3.dist-info/RECORD
