Metadata-Version: 2.1
Name: solidipy_mipt
Version: 1.2.3
Summary: Make your ML solid!
Home-page: https://github.com/Kynemallv/python_mipt_dafe/tree/main/homeworks/sem2_hw1/solidipy_framework
Author: Matvei Gorskii
Author-email: matveygor41@gmail.com
Project-URL: Bug Reports, https://github.com/Kynemallv/python_mipt_dafe/issues/new?labels=bug&template=bug-report---.md
Project-URL: Source, https://github.com/Kynemallv/python_mipt_dafe/tree/main/homeworks/sem2_hw1/solidipy_framework
Keywords: ml
Classifier: Development Status :: 3 - Alpha
Classifier: Intended Audience :: Developers
Classifier: Topic :: Scientific/Engineering :: Information Analysis
Classifier: License :: OSI Approved :: MIT License
Classifier: Programming Language :: Python :: 3.10
Classifier: Programming Language :: Python :: 3.11
Classifier: Programming Language :: Python :: 3.12
Classifier: Programming Language :: Python :: 3 :: Only
Requires-Python: >=3.10, <4
License-File: LICENSE.txt
Requires-Dist: numpy
Requires-Dist: matplotlib
Requires-Dist: scikit-learn
